hobase/__init__.py
hobase-1.0.1.dist-info/METADATA
hobase-1.0.1.dist-info/WHEEL
hobase-1.0.1.dist-info/RECORD
