Metadata-Version: 2.1
Name: hobase
Version: 1.0.1
Summary: A database based on sqlitedict and created to simplify the creation of discord bots
Author: KaBoT
Author-email: ac248384@gmail.com
Requires-Python: >=3.9,<4.0
Classifier: Programming Language :: Python :: 3
Classifier: Programming Language :: Python :: 3.9
Classifier: Programming Language :: Python :: 3.10
Classifier: Programming Language :: Python :: 3.11
Requires-Dist: sqlitedict (>=2.1.0,<3.0.0)
